worlddata/__init__.py
worlddata/worlddata.py
worlddata/APIExceptions/WorldDataExceptions.py
worlddata/APIExceptions/__init__.py
worlddata/APISections/__init__.py
worlddata/APISections/advance_search.py
worlddata/APISections/base.py
worlddata/APISections/search.py
worlddata/APISections/time_series.py
worlddata-0.0.6.dist-info/LICENSE.txt
worlddata-0.0.6.dist-info/METADATA
worlddata-0.0.6.dist-info/WHEEL
worlddata-0.0.6.dist-info/top_level.txt
worlddata-0.0.6.dist-info/RECORD
