Metadata-Version: 2.1
Name: worlddata
Version: 0.0.6
Summary: Python API wrapper for WorldData.AI
Home-page: https://github.com/worlddata-ai/python-api
Author: Akash Doifode
Author-email: akash.doifode@worlddata.ai
License: WorldData
Platform: UNKNOWN
Requires-Dist: requests
